larryc/__init__.py
larryc/__main__.py
larryc/app.py
larryc/enums.py
larryc-0.6.1.dist-info/LICENSE
larryc-0.6.1.dist-info/METADATA
larryc-0.6.1.dist-info/WHEEL
larryc-0.6.1.dist-info/top_level.txt
larryc-0.6.1.dist-info/RECORD
