Metadata-Version: 2.1
Name: larryc
Version: 0.6.1
Summary: Dictionary for your terminal
Home-page: https://github.com/furtidev/larryc
Author: furtidev (Isfer Hossain)
Author-email: <megaphone@poto.cafe>
Keywords: python,dictionary,cli,app,foss
Classifier: Development Status :: 4 - Beta
Classifier: Intended Audience :: End Users/Desktop
Classifier: Programming Language :: Python :: 3
Classifier: Operating System :: Unix
Classifier: Operating System :: MacOS :: MacOS X
Classifier: Operating System :: Microsoft :: Windows
License-File: LICENSE
Requires-Dist: rich
Requires-Dist: aiohttp
